{
  "symbols": [
    {
      "id": 3379,
      "symbol": "BB",
      "symbol_mic": "BB.XNYS",
      "symbol_display": "BB",
      "exchange": "NYSE",
      "region": "US",
      "logo_url": "https://logos.stocktwits-cdn.com/BB.png",
      "title": "BlackBerry Ltd",
      "aliases": [
        "RIMM",
        "BBRY"
      ],
      "deeplink": "symbol/BB",
      "external_id": null,
      "is_following": false,
      "watchlist_count": 147288,
      "has_pricing": true,
      "instrument_class": "Stock",
      "live_event": false,
      "sector": "TechnologyServices",
      "industry": "PackagedSoftware",
      "trending": true,
      "trending_score": 17.0121,
      "trends": {
        "all": 1,
        "region": 1,
        "exchange": 1,
        "class_all": 1,
        "class_equity": 1,
        "summary": "BlackBerry is experiencing a significant surge in trading volume and social sentiment as the community re-evaluates its QNX software as a critical, foundational layer for physical AI and robotics rather than a legacy telecommunications asset. Investors are increasingly optimistic about long-term institutional adoption and the company's role within major AI infrastructure ecosystems, driving strong bullish momentum.",
        "summary_at": "2026-05-25T06:27:03Z"
      },
      "trade_status": "FRACTIONAL",
      "features": {
        "alerts_price": true,
        "social_data": true,
        "trending_messages": true,
        "earnings": true
      },
      "cusip": "09228F103",
      "isin": "CA09228F1036",
      "should_seo_index": true,
      "rank": 1,
      "fundamentals": {
        "Symbol": "BB",
        "Name": "BlackBerry Ltd",
        "BusinessDescription": "BlackBerry Ltd. engages in the provision of intelligent security software and services. It operates through the following segments: QNX, Secure Communications, and Licensing. The QNX segment includes development of safe and reliable software for embedded systems across technology-driven industries. The Secure Communications segment delivers operational resiliency with a government-grade portfolio of secure, certified solutions for mobile fortification, critical communications and crisis management. The Licensing segment focuses on management and monetization of the firm's global patent portfolio. The company was founded by Michael Lazaridis, James Laurence Balsillie, and Douglas E. Fregin on March 7, 1984 and is headquartered in Waterloo, Canada.",
        "IndustryName": "Packaged Software",
        "SectorName": "Technology Services",
        "InstrumentClass": "Stock",
        "FiscalPeriodEndDate": "2/28/2026 12:00:00 AM",
        "TotalAssets": "1245.2",
        "TotalDebt": "224.8",
        "BookValuePerShare": "1.26994",
        "TotalExpenses": "483.000000002889",
        "TotalLiabilities": "499.2",
        "EnterpriseOverEBITDA": "",
        "RevenuePerEmployee": "313950.829",
        "GrossIncomeMargin": 74.0848661446002,
        "NumberOfEmployees": "1749",
        "RevenueToAssets": "0.441",
        "DividendsPerShareSecurity": "0",
        "DividendYieldSecurity": "0",
        "PriceToBook": 6.2286,
        "SalesOrRevenue": "549.1",
        "TotalCash": "274.7",
        "SharesOutstanding": "587.43112",
        "EPS": 0.089,
        "MarketCapitalization": "4635.7425",
        "PEGRatio": "0.25",
        "PERatio": 91.87,
        "FloatCurrent": "584.111",
        "AverageDailyVolumeLastMonth": 17179290.3099,
        "50DayMovingAverage": 4.7286,
        "Beta": 1.5096,
        "AverageDailyVolumeLast3Months": "16550729.014",
        "HighPriceLast52Weeks": 8.03,
        "LowPriceLast52Weeks": 3.1201,
        "TotalEnterpriseValue": "1893.58244308391",
        "5YearAveragePERatio": "182.39",
        "SharesHeldByInstitutions": 260.710308,
        "EarningsGrowth": "159.4327",
        "DividendRate": 0,
        "DividendPayoutRatio": "0",
        "LastUpdated": "05/25/2026",
        "MarketCap": 4635.7425,
        "EBITDA": null
      },
      "direction": "bullish",
      "arrow": "▲",
      "quoteType": "EQUITY",
      "marketState": "CLOSED",
      "regularPrice": 7.91,
      "extendedPrice": 7.99,
      "displayPrice": 7.99,
      "displaySession": "After Hours",
      "regularChangePct": 18.947368421052627,
      "extendedChangePct": 1.011378002528446,
      "displayChangePct": 1.011378002528446,
      "lastUpdated": "2026-05-26T03:58:58.383Z"
    },
    {
      "id": 20910,
      "symbol": "RDW",
      "symbol_mic": "RDW.XNYS",
      "symbol_display": "RDW",
      "exchange": "NYSE",
      "region": "US",
      "logo_url": "https://logos.stocktwits-cdn.com/RDW.png",
      "title": "Redwire Corp",
      "aliases": [],
      "deeplink": "symbol/RDW",
      "external_id": null,
      "is_following": false,
      "watchlist_count": 18292,
      "has_pricing": true,
      "instrument_class": "Stock",
      "live_event": false,
      "sector": "ElectronicTechnology",
      "industry": "AerospaceAndDefense",
      "trending": true,
      "trending_score": 11.731,
      "trends": {
        "all": 2,
        "region": 2,
        "exchange": 2,
        "class_all": 2,
        "class_equity": 2,
        "summary": "Redwire Corp is seeing significant momentum as investors pivot toward the space infrastructure sector, fueled by defense contract wins and anticipation surrounding the upcoming SpaceX IPO. Community sentiment is largely bullish, with many participants actively discussing the stock's potential for a long-term re-rating as they draw comparisons to other high-growth space stocks.",
        "summary_at": "2026-05-25T07:32:12Z"
      },
      "trade_status": "WHOLE",
      "features": {
        "alerts_price": true,
        "social_data": true,
        "trending_messages": true,
        "earnings": true
      },
      "cusip": "75776W103",
      "isin": "US75776W1036",
      "should_seo_index": true,
      "rank": 2,
      "fundamentals": {
        "Symbol": "RDW",
        "Name": "Redwire Corporation",
        "BusinessDescription": "Redwire Corp. manufactures and supplies space equipment. It offers critical space solutions and reliability components for the next generation space economy with IP for solar power generation and in-space 3D printing and manufacturing. It assists its customers in solving challenges of future space missions. The company was founded in 2020 and is headquartered in Jacksonville, FL.",
        "IndustryName": "Aerospace And Defense",
        "SectorName": "Electronic Technology",
        "InstrumentClass": "Stock",
        "FiscalPeriodEndDate": "12/31/2025 12:00:00 AM",
        "TotalAssets": "1510.975",
        "TotalDebt": "200.833",
        "BookValuePerShare": "5.52334",
        "TotalExpenses": "501.25",
        "TotalLiabilities": "450.959",
        "EnterpriseOverEBITDA": "",
        "RevenuePerEmployee": "237858.865",
        "GrossIncomeMargin": 5.15383996111884,
        "NumberOfEmployees": "1410",
        "RevenueToAssets": "0.2455",
        "DividendsPerShareSecurity": "0",
        "DividendYieldSecurity": "0",
        "PriceToBook": 3.1824,
        "SalesOrRevenue": "335.381",
        "TotalCash": "95.183",
        "SharesOutstanding": "191.915804",
        "EPS": -2.2781,
        "MarketCapitalization": "3479.088572",
        "PERatio": -6.51,
        "FloatCurrent": "187.57",
        "AverageDailyVolumeLastMonth": 23693392.3826,
        "50DayMovingAverage": 10.397,
        "Beta": 2.6052,
        "AverageDailyVolumeLast3Months": "25977501.4255",
        "HighPriceLast52Weeks": 22.25,
        "LowPriceLast52Weeks": 4.87,
        "TotalEnterpriseValue": "1014.1864368",
        "SharesHeldByInstitutions": 99.381634,
        "EarningsGrowth": "-18.9757",
        "DividendRate": 0,
        "LastUpdated": "05/25/2026",
        "MarketCap": 3479.088572,
        "EBITDA": null
      },
      "direction": "bullish",
      "arrow": "▲",
      "quoteType": "EQUITY",
      "marketState": "CLOSED",
      "regularPrice": 17.49,
      "extendedPrice": 17.5326,
      "displayPrice": 17.5326,
      "displaySession": "After Hours",
      "regularChangePct": 13.94136807817589,
      "extendedChangePct": 0.2435677530017164,
      "displayChangePct": 0.2435677530017164,
      "lastUpdated": "2026-05-26T03:58:58.383Z"
    },
    {
      "id": 13817,
      "symbol": "PSKY",
      "symbol_mic": "NASDAQ",
      "symbol_display": "PSKY",
      "exchange": "NASDAQ",
      "region": "US",
      "logo_url": "https://logos.stocktwits-cdn.com/PARA.png",
      "title": "Paramount Skydance Corp. - Ordinary Shares - Class B",
      "aliases": [],
      "deeplink": "symbol/PSKY",
      "external_id": null,
      "is_following": false,
      "watchlist_count": 26484,
      "has_pricing": true,
      "instrument_class": "Stock",
      "live_event": false,
      "sector": "ConsumerServices",
      "industry": "Broadcasting",
      "trending": true,
      "trending_score": 4.40002,
      "trends": null,
      "trade_status": "FRACTIONAL",
      "features": {
        "alerts_price": true,
        "social_data": true,
        "trending_messages": true,
        "earnings": false
      },
      "cusip": "69932A204",
      "isin": "US69932A2042",
      "should_seo_index": true,
      "rank": 3,
      "fundamentals": {
        "Symbol": "PSKY",
        "Name": "Paramount Skydance Corp. - Ordinary Shares - Class B",
        "BusinessDescription": "Paramount Skydance Corp. is a next-generation global media and entertainment company that engages in providing content creation and distribution services. It operates through the following business segments: Studios, Direct-to-Consumer, and TV Media. Its portfolio unites brands including Paramount Pictures, Paramount Television, CBS, CBS News, Nickelodeon, MTV, BET, Comedy Central, Showtime, Paramount Plus, Pluto TV, and Skydance’s Animation, Film, Television, Interactive/Games, and Sports divisions. The company was founded on June 3, 2024 and is headquartered in New York, NY.",
        "IndustryName": "Cable Or Satellite TV",
        "SectorName": "Consumer Services",
        "InstrumentClass": "Stock",
        "FiscalPeriodEndDate": "12/31/2025 12:00:00 AM",
        "TotalAssets": "43342",
        "TotalDebt": "15092",
        "BookValuePerShare": "10.55325",
        "TotalExpenses": "26650",
        "TotalLiabilities": "30455",
        "EnterpriseOverEBITDA": "",
        "RevenuePerEmployee": "1641534.091",
        "GrossIncomeMargin": 28.9398082447821,
        "NumberOfEmployees": "17600",
        "RevenueToAssets": "0.6529",
        "DividendsPerShareSecurity": "0.2",
        "DividendExDate": "12/18/2025 00:00:00",
        "DividendYieldSecurity": "1.49253731343284",
        "PriceToBook": 0.9991,
        "SalesOrRevenue": "28891",
        "TotalCash": "3274",
        "SharesOutstanding": "1108",
        "EPS": -0.5605,
        "MarketCapitalization": "11706.550257",
        "PEGRatio": "0.11",
        "PERatio": -20.23,
        "FloatCurrent": "865.349",
        "AverageDailyVolumeLastMonth": 11086430.6292,
        "50DayMovingAverage": 10.2984,
        "Beta": 0.6278,
        "AverageDailyVolumeLast3Months": "13455593.6053",
        "HighPriceLast52Weeks": 20.86,
        "LowPriceLast52Weeks": 8.615,
        "TotalEnterpriseValue": "27859.2",
        "5YearAveragePERatio": "7.44",
        "SharesHeldByInstitutions": 325.333737,
        "EarningsGrowth": "93.7319",
        "DividendRate": 0.2,
        "LastUpdated": "05/25/2026",
        "MarketCap": 11706.550257,
        "EBITDA": null
      },
      "direction": "bearish",
      "arrow": "▼",
      "quoteType": "EQUITY",
      "marketState": "CLOSED",
      "regularPrice": 10.46,
      "extendedPrice": 10.4309,
      "displayPrice": 10.4309,
      "displaySession": "After Hours",
      "regularChangePct": 1.750972762645929,
      "extendedChangePct": -0.27820267686425865,
      "displayChangePct": -0.27820267686425865,
      "lastUpdated": "2026-05-26T03:58:58.383Z"
    },
    {
      "id": 16505,
      "symbol": "NVTS",
      "symbol_mic": "NVTS.XNAS",
      "symbol_display": "NVTS",
      "exchange": "NASDAQ",
      "region": "US",
      "logo_url": "https://logos.stocktwits-cdn.com/NVTS.png",
      "title": "Navitas Semiconductor Corp",
      "aliases": [],
      "deeplink": "symbol/NVTS",
      "external_id": null,
      "is_following": false,
      "watchlist_count": 24671,
      "has_pricing": true,
      "instrument_class": "Stock",
      "live_event": false,
      "sector": "ElectronicTechnology",
      "industry": "Semiconductors",
      "trending": true,
      "trending_score": 7.63338,
      "trends": {
        "all": 5,
        "region": 4,
        "exchange": 2,
        "class_all": 5,
        "class_equity": 4,
        "summary": "Navitas Semiconductor is experiencing significant volatility driven by a $125 million share offering following a recent rally tied to AI data center and semiconductor partnerships. While bullish investors view the company as a key player in the GaN and SiC power architecture market with strong long-term growth potential, the community remains deeply divided, with bears pointing to dilution risks and a disconnect between current revenue and market valuation.",
        "summary_at": "2026-05-22T17:47:14Z"
      },
      "trade_status": "WHOLE",
      "features": {
        "alerts_price": true,
        "social_data": true,
        "trending_messages": true,
        "earnings": true
      },
      "cusip": "63942X106",
      "isin": "US63942X1063",
      "should_seo_index": true,
      "rank": 4,
      "fundamentals": {
        "Symbol": "NVTS",
        "Name": "Navitas Semiconductor Corp",
        "BusinessDescription": "Navitas Semiconductor Corp. engages in the development of ultra-efficient gallium nitride (GaN) semiconductors. Its GaN power ICs integrate GaN power with drive, control and protection to enable charging, power density, and energy savings for mobile, consumer, enterprise, eMobility and new energy markets. The company was founded by Daniel Kinzer, Nick Fichtenbaum, Gene Sheridan, and Jason Zhang on August 12, 2020 and is headquartered in Torrance, CA.",
        "IndustryName": "Semiconductors",
        "SectorName": "Electronic Technology",
        "InstrumentClass": "Stock",
        "FiscalPeriodEndDate": "12/31/2025 12:00:00 AM",
        "TotalAssets": "578.563",
        "TotalDebt": "6.472",
        "BookValuePerShare": "1.92456",
        "TotalExpenses": "133.731",
        "TotalLiabilities": "134.902",
        "EnterpriseOverEBITDA": "",
        "RevenuePerEmployee": "241663.158",
        "GrossIncomeMargin": -10.2121264918547,
        "NumberOfEmployees": "190",
        "RevenueToAssets": "0.0841",
        "DividendsPerShareSecurity": "0",
        "DividendYieldSecurity": "0",
        "PriceToBook": 16.1556,
        "SalesOrRevenue": "45.916",
        "TotalCash": "238.602",
        "SharesOutstanding": "230.525464",
        "EPS": -0.5689,
        "MarketCapitalization": "6836.110085",
        "PEGRatio": "-0.31",
        "PERatio": -46.64,
        "FloatCurrent": "210.898",
        "AverageDailyVolumeLastMonth": 32257542.711,
        "50DayMovingAverage": 14.1867,
        "Beta": 2.7874,
        "AverageDailyVolumeLast3Months": "29511781.1698",
        "HighPriceLast52Weeks": 29.5,
        "LowPriceLast52Weeks": 4.535,
        "TotalEnterpriseValue": "1235.66122",
        "5YearAveragePERatio": "6.92",
        "SharesHeldByInstitutions": 105.016459,
        "EarningsGrowth": "-19.2432",
        "DividendRate": 0,
        "LastUpdated": "05/25/2026",
        "MarketCap": 6836.110085,
        "EBITDA": null
      },
      "direction": "bearish",
      "arrow": "▼",
      "quoteType": "EQUITY",
      "marketState": "CLOSED",
      "regularPrice": 29.25,
      "extendedPrice": 29.0115,
      "displayPrice": 29.0115,
      "displaySession": "After Hours",
      "regularChangePct": 19.97538474260112,
      "extendedChangePct": -0.8153846153846098,
      "displayChangePct": -0.8153846153846098,
      "lastUpdated": "2026-05-26T03:58:58.383Z"
    },
    {
      "id": 24894,
      "symbol": "LUNR",
      "symbol_mic": "LUNR.XNAS",
      "symbol_display": "LUNR",
      "exchange": "NASDAQ",
      "region": "US",
      "logo_url": "https://logos.stocktwits-cdn.com/LUNR.png",
      "title": "Intuitive Machines Inc",
      "aliases": [],
      "deeplink": "symbol/LUNR",
      "external_id": null,
      "is_following": false,
      "watchlist_count": 36452,
      "has_pricing": true,
      "instrument_class": "Stock",
      "live_event": false,
      "sector": "ElectronicTechnology",
      "industry": "AerospaceAndDefense",
      "trending": true,
      "trending_score": 7.167,
      "trends": {
        "all": 7,
        "region": 6,
        "exchange": 3,
        "class_all": 7,
        "class_equity": 6,
        "summary": "Intuitive Machines is rallying as investors anticipate a major contract award for NASA's Lunar Terrain Vehicle program, following recent expansion through strategic acquisitions like Goonhilly Earth Station. The stock is benefiting from intense community sentiment fueled by positive institutional analyst revisions and the broader momentum surrounding the upcoming SpaceX IPO.",
        "summary_at": "2026-05-23T04:57:06Z"
      },
      "trade_status": "WHOLE",
      "features": {
        "alerts_price": true,
        "social_data": true,
        "trending_messages": true,
        "earnings": true
      },
      "cusip": "46125A100",
      "isin": "US46125A1007",
      "should_seo_index": true,
      "rank": 5,
      "fundamentals": {
        "Symbol": "LUNR",
        "Name": "Intuitive Machines Inc - Ordinary Shares - Class A",
        "BusinessDescription": "Intuitive Machines, Inc. is a space exploration, infrastructure, and services company, which engages in contributing to the establishment of cislunar infrastructure and helping to develop cislunar and deep space commerce. It offers space products and services. The company was founded by Stephen J. Altemus, Kam Ghaffarian, and Timothy P. Crain in 2013 and is headquartered in Houston, TX.",
        "IndustryName": "Aerospace And Defense",
        "SectorName": "Electronic Technology",
        "InstrumentClass": "Stock",
        "FiscalPeriodEndDate": "12/31/2025 12:00:00 AM",
        "TotalAssets": "757.16",
        "TotalDebt": "372.159",
        "BookValuePerShare": "-6.22487",
        "TotalExpenses": "286.508",
        "TotalLiabilities": "553.458",
        "EnterpriseOverEBITDA": "",
        "RevenuePerEmployee": "400112.381",
        "GrossIncomeMargin": 2.56737392827729,
        "NumberOfEmployees": "525",
        "RevenueToAssets": "0.1946",
        "DividendsPerShareSecurity": "0",
        "DividendYieldSecurity": "0",
        "PriceToBook": -18.2913,
        "SalesOrRevenue": "210.059",
        "TotalCash": "585.339",
        "SharesOutstanding": "121.28188",
        "EPS": -0.727,
        "MarketCapitalization": "8303.221423",
        "PEGRatio": "0.39",
        "PERatio": -43.9,
        "FloatCurrent": "151.396",
        "AverageDailyVolumeLastMonth": 15992916.3018,
        "50DayMovingAverage": 25.248,
        "Beta": 2.5699,
        "AverageDailyVolumeLast3Months": "13803660.2834",
        "HighPriceLast52Weeks": 38.55,
        "LowPriceLast52Weeks": 7.78,
        "TotalEnterpriseValue": "2618.8600426",
        "5YearAveragePERatio": "1.1",
        "SharesHeldByInstitutions": 111.626627,
        "EarningsGrowth": "58.3166",
        "DividendRate": 0,
        "LastUpdated": "05/25/2026",
        "MarketCap": 8303.221423,
        "EBITDA": null
      },
      "direction": "bearish",
      "arrow": "▼",
      "quoteType": "EQUITY",
      "marketState": "CLOSED",
      "regularPrice": 38.26,
      "extendedPrice": 38.15,
      "displayPrice": 38.15,
      "displaySession": "After Hours",
      "regularChangePct": 11.740660732515224,
      "extendedChangePct": -0.287506534239413,
      "displayChangePct": -0.287506534239413,
      "lastUpdated": "2026-05-26T03:58:58.383Z"
    },
    {
      "id": 8404,
      "symbol": "GRPN",
      "symbol_mic": "GRPN.XNAS",
      "symbol_display": "GRPN",
      "exchange": "NASDAQ",
      "region": "US",
      "logo_url": "https://logos.stocktwits-cdn.com/GRPN.png",
      "title": "Groupon Inc",
      "aliases": [],
      "deeplink": "symbol/GRPN",
      "external_id": null,
      "is_following": false,
      "watchlist_count": 37125,
      "has_pricing": true,
      "instrument_class": "Stock",
      "live_event": false,
      "earnings_cta": "res_earn_tab",
      "earnings_id": "066cd0af-2dd5-4f16-9210-cd82ed7bf083",
      "sector": "RetailTrade",
      "industry": "InternetRetail",
      "trending": true,
      "trending_score": 4.1507,
      "trends": null,
      "trade_status": "FRACTIONAL",
      "features": {
        "alerts_price": true,
        "social_data": true,
        "trending_messages": true,
        "earnings": true
      },
      "cusip": "399473206",
      "isin": "US3994732069",
      "should_seo_index": true,
      "rank": 6,
      "fundamentals": {
        "Symbol": "GRPN",
        "Name": "Groupon Inc",
        "BusinessDescription": "Groupon, Inc. engages in the global scaled two-sided marketplace that connects consumers to merchants. It operates through the North America and International geographical segments. The company was founded by Andrew D. Mason, Eric Paul Lefkofsky, and Bradley A. Keywell in October 2008 and is headquartered in Chicago, IL.",
        "IndustryName": "Internet Retail",
        "SectorName": "Retail Trade",
        "InstrumentClass": "Stock",
        "FiscalPeriodEndDate": "12/31/2025 12:00:00 AM",
        "TotalAssets": "670.406",
        "TotalDebt": "349.599",
        "BookValuePerShare": "-1.04492",
        "TotalExpenses": "485.466",
        "TotalLiabilities": "712.796",
        "EnterpriseOverEBITDA": "",
        "RevenuePerEmployee": "287440.6",
        "GrossIncomeMargin": 88.9742025833531,
        "NumberOfEmployees": "1734",
        "RevenueToAssets": "0.8365",
        "DividendsPerShareSecurity": "0",
        "DividendYieldSecurity": "0",
        "PriceToBook": -11.7472,
        "SalesOrRevenue": "498.422",
        "TotalCash": "325.612",
        "SharesOutstanding": "40.732313",
        "EPS": -2.0725,
        "MarketCapitalization": "719.036792",
        "PEGRatio": "-0.12",
        "PERatio": -7.24,
        "FloatCurrent": "22.9322",
        "AverageDailyVolumeLastMonth": 2114652.0289,
        "50DayMovingAverage": 13.9248,
        "Beta": 1.2232,
        "AverageDailyVolumeLast3Months": "1916335.7221",
        "HighPriceLast52Weeks": 43.08,
        "LowPriceLast52Weeks": 9.17,
        "TotalEnterpriseValue": "733.83893586",
        "5YearAveragePERatio": "6.29",
        "SharesHeldByInstitutions": 26.392833,
        "EarningsGrowth": "-175.2135",
        "DividendRate": 0,
        "LastUpdated": "05/25/2026",
        "MarketCap": 719.036792,
        "EBITDA": null
      },
      "direction": "bearish",
      "arrow": "▼",
      "quoteType": "EQUITY",
      "marketState": "CLOSED",
      "regularPrice": 18.93,
      "extendedPrice": 18.841,
      "displayPrice": 18.841,
      "displaySession": "After Hours",
      "regularChangePct": 3.89681098261191,
      "extendedChangePct": -0.4701531959852015,
      "displayChangePct": -0.4701531959852015,
      "lastUpdated": "2026-05-26T03:58:58.383Z"
    },
    {
      "id": 191640,
      "symbol": "CGCT",
      "symbol_mic": "CGCT.XNAS",
      "symbol_display": "CGCT",
      "exchange": "NASDAQ",
      "region": "US",
      "logo_url": "https://logos.stocktwits-cdn.com/CGCT.webp",
      "title": "Cartesian Growth Corporation III",
      "aliases": [],
      "deeplink": "symbol/CGCT",
      "external_id": null,
      "is_following": false,
      "watchlist_count": 78,
      "has_pricing": true,
      "instrument_class": "Stock",
      "live_event": false,
      "sector": "Finance",
      "industry": "FinancialConglomerates",
      "trending": true,
      "trending_score": 6.11645,
      "trends": {
        "all": 9,
        "region": 8,
        "exchange": 4,
        "class_all": 9,
        "class_equity": 8,
        "summary": "Cartesian Growth Corporation III is gaining attention as it prepares to take solid-state battery developer Factorial public via SPAC. Investors are actively discussing the company's high-profile automotive and defense partnerships, alongside significant insider buying that has bolstered confidence in its long-term growth potential.",
        "summary_at": "2026-05-23T05:07:03Z"
      },
      "features": {
        "alerts_price": true,
        "social_data": true,
        "trending_messages": false,
        "earnings": false
      },
      "cusip": null,
      "isin": null,
      "should_seo_index": true,
      "rank": 7,
      "fundamentals": {
        "Symbol": "CGCT",
        "Name": "Cartesian Growth Corp III - Ordinary Shares- Class A",
        "BusinessDescription": "Cartesian Growth Corp. III is a blank check company. It was created for the purpose of effecting a merger, amalgamation, share exchange, asset acquisition, share purchase, reorganization or similar business combination. The company was founded on October 29, 2024 and is headquartered in New York, NY.",
        "IndustryName": "Financial Conglomerates",
        "SectorName": "Finance",
        "InstrumentClass": "Stock",
        "FiscalPeriodEndDate": "12/31/2025 12:00:00 AM",
        "TotalAssets": "284.15485",
        "TotalDebt": "0",
        "BookValuePerShare": "7.8313",
        "TotalExpenses": "1.158207",
        "TotalLiabilities": "13.974869",
        "EnterpriseOverEBITDA": "",
        "RevenuePerEmployee": "0",
        "NumberOfEmployees": "2",
        "RevenueToAssets": "0",
        "DividendsPerShareSecurity": "0",
        "DividendYieldSecurity": "0",
        "PriceToBook": 1.2513,
        "SalesOrRevenue": "0",
        "TotalCash": "0.624163",
        "SharesOutstanding": "34.5",
        "EPS": 0.1803,
        "MarketCapitalization": "340.169992",
        "PERatio": 42.94,
        "FloatCurrent": "19.229",
        "AverageDailyVolumeLastMonth": 264340.6782,
        "50DayMovingAverage": 10.3027,
        "Beta": 0.7799,
        "AverageDailyVolumeLast3Months": "202555.8259",
        "HighPriceLast52Weeks": 10.44,
        "LowPriceLast52Weeks": 9.26,
        "TotalEnterpriseValue": "354.553337",
        "5YearAveragePERatio": "57.1",
        "SharesHeldByInstitutions": 29.081361,
        "DividendRate": 0,
        "DividendPayoutRatio": "0",
        "LastUpdated": "05/25/2026",
        "MarketCap": 340.169992,
        "EBITDA": null,
        "GrossIncomeMargin": null
      },
      "direction": "bullish",
      "arrow": "▲",
      "quoteType": "EQUITY",
      "marketState": "CLOSED",
      "regularPrice": 9.86,
      "extendedPrice": 10.0463,
      "displayPrice": 10.0463,
      "displaySession": "After Hours",
      "regularChangePct": -5.0096247600794594,
      "extendedChangePct": 1.8894523326572112,
      "displayChangePct": 1.8894523326572112,
      "lastUpdated": "2026-05-26T03:58:58.383Z"
    },
    {
      "id": 22978,
      "symbol": "SIDU",
      "symbol_mic": "SIDU.XNAS",
      "symbol_display": "SIDU",
      "exchange": "NASDAQ",
      "region": "US",
      "logo_url": "https://logos.stocktwits-cdn.com/SIDU.webp",
      "title": "Sidus Space Inc - Ordinary Shares - Class A",
      "aliases": [],
      "deeplink": "symbol/SIDU",
      "external_id": null,
      "is_following": false,
      "watchlist_count": 13651,
      "has_pricing": true,
      "instrument_class": "Stock",
      "live_event": false,
      "sector": "ElectronicTechnology",
      "industry": "TelecommunicationsEquipment",
      "trending": true,
      "trending_score": 7.78643,
      "trends": {
        "all": 4,
        "region": 3,
        "exchange": 1,
        "class_all": 4,
        "class_equity": 3,
        "summary": "Sidus Space is trending due to intense speculation surrounding its position as a high-leverage, low-float play in the aerospace sector ahead of the highly anticipated SpaceX IPO. The community is heavily focused on the stock's potential for a major technical breakout, with discussions centering on its recent operational updates, institutional accumulation, and the belief that the broader space economy is reaching an inflection point.",
        "summary_at": "2026-05-24T07:13:42Z"
      },
      "trade_status": "WHOLE",
      "features": {
        "alerts_price": true,
        "social_data": true,
        "trending_messages": true,
        "earnings": true
      },
      "cusip": "826165201",
      "isin": "US8261652015",
      "should_seo_index": true,
      "rank": 8,
      "fundamentals": {
        "Symbol": "SIDU",
        "Name": "Sidus Space Inc - Ordinary Shares - Class A",
        "BusinessDescription": "Sidus Space, Inc. is a space-as-a-service company. The firm focuses on commercial satellite design, manufacture, launch planning, mission operations and in-orbit support, and data collection with a vision to demonstrate space operations for new technologies, and deliver data and predictive analytics to both domestic and global customers. The company was founded by Carol M. Craig on July 17, 2012 and is headquartered in Merritt Island, FL.",
        "IndustryName": "Telecommunications Equipment",
        "SectorName": "Electronic Technology",
        "InstrumentClass": "Stock",
        "FiscalPeriodEndDate": "12/31/2025 12:00:00 AM",
        "TotalAssets": "66.090711",
        "TotalDebt": "8.948628",
        "BookValuePerShare": "0.77396",
        "TotalExpenses": "26.881334",
        "TotalLiabilities": "15.455434",
        "EnterpriseOverEBITDA": "",
        "RevenuePerEmployee": "34180.586",
        "GrossIncomeMargin": -168.226129901846,
        "NumberOfEmployees": "99",
        "RevenueToAssets": "0.0679",
        "DividendsPerShareSecurity": "0",
        "DividendYieldSecurity": "0",
        "PriceToBook": 7.1917,
        "SalesOrRevenue": "3.383878",
        "TotalCash": "43.175996",
        "SharesOutstanding": "65.424055",
        "EPS": -1.191,
        "MarketCapitalization": "414.028045",
        "PERatio": -5.46,
        "FloatCurrent": "80.5798",
        "AverageDailyVolumeLastMonth": 32430236.4988,
        "50DayMovingAverage": 3.4118,
        "Beta": 1.7857,
        "AverageDailyVolumeLast3Months": "18903006.0252",
        "HighPriceLast52Weeks": 5.99,
        "LowPriceLast52Weeks": 0.6278,
        "TotalEnterpriseValue": "43.47900642",
        "SharesHeldByInstitutions": 12.032114,
        "EarningsGrowth": "64.7671",
        "DividendRate": 0,
        "LastUpdated": "05/25/2026",
        "MarketCap": 414.028045,
        "EBITDA": null
      },
      "direction": "bearish",
      "arrow": "▼",
      "quoteType": "EQUITY",
      "marketState": "CLOSED",
      "regularPrice": 5.12,
      "extendedPrice": 4.9605,
      "displayPrice": 4.9605,
      "displaySession": "After Hours",
      "regularChangePct": 23.97094430992737,
      "extendedChangePct": -3.115234375000008,
      "displayChangePct": -3.115234375000008,
      "lastUpdated": "2026-05-26T03:58:58.383Z"
    },
    {
      "id": 15711,
      "symbol": "HYLN",
      "symbol_mic": "HYLN.XASE",
      "symbol_display": "HYLN",
      "exchange": "NYSEMkt",
      "region": "US",
      "logo_url": "https://logos.stocktwits-cdn.com/HYLN.png",
      "title": "Hyliion Holdings Corp",
      "aliases": [],
      "deeplink": "symbol/HYLN",
      "external_id": null,
      "is_following": false,
      "watchlist_count": 38547,
      "has_pricing": true,
      "instrument_class": "Stock",
      "live_event": false,
      "sector": "ProducerManufacturing",
      "industry": "AutoPartsOEM",
      "trending": true,
      "trending_score": 2.74848,
      "trends": null,
      "trade_status": "WHOLE",
      "features": {
        "alerts_price": false,
        "social_data": true,
        "trending_messages": true,
        "earnings": true
      },
      "cusip": "449109107",
      "isin": "US4491091074",
      "should_seo_index": true,
      "rank": 9,
      "fundamentals": {
        "Symbol": "HYLN",
        "Name": "Hyliion Holdings Corporation - Ordinary Shares - Class A",
        "BusinessDescription": "Hyliion Holdings Corp. engages in the development of sustainable electricity-producing technology. It focuses on providing modular power plant technology that can operate on various fuel sources through the KARNO power module. The company was founded by Thomas J. Healy in 2015 and is headquartered in Cedar Park, TX.",
        "IndustryName": "Auto Parts OEM",
        "SectorName": "Producer Manufacturing",
        "InstrumentClass": "Stock",
        "FiscalPeriodEndDate": "12/31/2025 12:00:00 AM",
        "TotalAssets": "203.559",
        "TotalDebt": "4.372",
        "BookValuePerShare": "1.08315",
        "TotalExpenses": "68.529",
        "TotalLiabilities": "11.55",
        "EnterpriseOverEBITDA": "",
        "RevenuePerEmployee": "30752.212",
        "GrossIncomeMargin": -166.503597122302,
        "NumberOfEmployees": "113",
        "RevenueToAssets": "0.0305",
        "DividendsPerShareSecurity": "0",
        "DividendYieldSecurity": "0",
        "PriceToBook": 5.8777,
        "SalesOrRevenue": "3.475",
        "TotalCash": "22.938",
        "SharesOutstanding": "177.26872",
        "EPS": -0.326,
        "MarketCapitalization": "1068.180127",
        "PEGRatio": "24.03",
        "PERatio": -20.43,
        "FloatCurrent": "123.474",
        "AverageDailyVolumeLastMonth": 728542.6109,
        "50DayMovingAverage": 2.3338,
        "Beta": 2.1573,
        "AverageDailyVolumeLast3Months": "1864224.3517",
        "HighPriceLast52Weeks": 6.24,
        "LowPriceLast52Weeks": 1.14,
        "TotalEnterpriseValue": "234.7920084",
        "SharesHeldByInstitutions": 44.556059,
        "EarningsGrowth": "5.0518",
        "DividendRate": 0,
        "LastUpdated": "05/25/2026",
        "MarketCap": 1068.180127,
        "EBITDA": null
      },
      "direction": "bearish",
      "arrow": "▼",
      "quoteType": "EQUITY",
      "marketState": "CLOSED",
      "regularPrice": 5.99,
      "extendedPrice": 5.93,
      "displayPrice": 5.93,
      "displaySession": "After Hours",
      "regularChangePct": 42.61904761904762,
      "extendedChangePct": -1.0016694490818112,
      "displayChangePct": -1.0016694490818112,
      "lastUpdated": "2026-05-26T03:58:58.383Z"
    },
    {
      "id": 15968,
      "symbol": "MNTS",
      "symbol_mic": "MNTS.XNAS",
      "symbol_display": "MNTS",
      "exchange": "NASDAQ",
      "region": "US",
      "logo_url": "https://logos.stocktwits-cdn.com/MNTS.png",
      "title": "Momentus Inc - Ordinary Shares - Class A",
      "aliases": [],
      "deeplink": "symbol/MNTS",
      "external_id": null,
      "is_following": false,
      "watchlist_count": 14750,
      "has_pricing": true,
      "instrument_class": "Stock",
      "live_event": false,
      "earnings_cta": "up_earn_tab",
      "earnings_id": null,
      "sector": "ElectronicTechnology",
      "industry": "AerospaceAndDefense",
      "trending": true,
      "trending_score": 6.03345,
      "trends": {
        "all": 10,
        "region": 9,
        "exchange": 5,
        "class_all": 10,
        "class_equity": 9,
        "summary": "Momentus Inc. is trending as investors aggressively position themselves ahead of the upcoming SpaceX IPO, viewing the company as a high-leverage \"space-tug\" infrastructure play with a low market cap. The community is heavily focused on the company's recent debt retirement, insider accumulation, and critical orbital successes, with active discussions centering on the potential for a short squeeze due to limited float.",
        "summary_at": "2026-05-25T03:52:15Z"
      },
      "trade_status": "WHOLE",
      "features": {
        "alerts_price": true,
        "social_data": true,
        "trending_messages": false,
        "earnings": true
      },
      "cusip": "60879E200",
      "isin": "US60879E2000",
      "should_seo_index": true,
      "rank": 10,
      "fundamentals": {
        "Symbol": "MNTS",
        "Name": "Momentus Inc - Ordinary Shares - Class A",
        "BusinessDescription": "Momentus, Inc. engages in the provision of in-space infrastructure services. It offers space transportation and in-orbit servicing. The company was founded by Mikhail Kokorich in 2017 and is headquartered in Santa Jose, CA.",
        "IndustryName": "Aerospace And Defense",
        "SectorName": "Electronic Technology",
        "InstrumentClass": "Stock",
        "FiscalPeriodEndDate": "12/31/2025 12:00:00 AM",
        "TotalAssets": "42.158",
        "TotalDebt": "11.302",
        "BookValuePerShare": "7.91482",
        "TotalExpenses": "28.365",
        "TotalLiabilities": "25.018",
        "EnterpriseOverEBITDA": "",
        "RevenuePerEmployee": "31714.286",
        "GrossIncomeMargin": -37.2072072072072,
        "NumberOfEmployees": "35",
        "RevenueToAssets": "0.0873",
        "DividendsPerShareSecurity": "0",
        "DividendYieldSecurity": "0",
        "PriceToBook": 1.5866,
        "SalesOrRevenue": "1.11",
        "TotalCash": "12.861",
        "SharesOutstanding": "2.165559",
        "EPS": -48.9102,
        "MarketCapitalization": "73.7439",
        "PEGRatio": "1.76",
        "PERatio": -0.16,
        "FloatCurrent": "9.9605",
        "AverageDailyVolumeLastMonth": 3640803.9925,
        "50DayMovingAverage": 4.979,
        "Beta": 2.2599,
        "AverageDailyVolumeLast3Months": "2064562.7026",
        "HighPriceLast52Weeks": 43.554,
        "LowPriceLast52Weeks": 3.11,
        "TotalEnterpriseValue": "1.47470319",
        "5YearAveragePERatio": "2.46",
        "SharesHeldByInstitutions": 0.641097,
        "EarningsGrowth": "85.5784",
        "DividendRate": 0,
        "LastUpdated": "05/25/2026",
        "MarketCap": 73.7439,
        "EBITDA": null
      },
      "direction": "bearish",
      "arrow": "▼",
      "quoteType": "EQUITY",
      "marketState": "CLOSED",
      "regularPrice": 7.38,
      "extendedPrice": 7.3384,
      "displayPrice": 7.3384,
      "displaySession": "After Hours",
      "regularChangePct": -2.251655629139072,
      "extendedChangePct": -0.5636856368563666,
      "displayChangePct": -0.5636856368563666,
      "lastUpdated": "2026-05-26T03:58:58.383Z"
    }
  ],
  "fetchedAt": "2026-05-26T03:58:58.383Z",
  "source": "stocktwits+yfinance-proxy"
}